cmdcmd/__init__.py
cmdcmd/cmd.py
cmdcmd-3.dist-info/METADATA
cmdcmd-3.dist-info/WHEEL
cmdcmd-3.dist-info/top_level.txt
cmdcmd-3.dist-info/RECORD
