Metadata-Version: 2.1
Name: cmdcmd
Version: 3
Summary: Ergonomic command line interface parser
Home-page: https://github.com/aperezdc/python-cmdcmd
Author: Adrian Perez de Castro
Author-email: aperez@igalia.com
License: UNKNOWN
Platform: UNKNOWN
Classifier: Development Status :: 4 - Beta
Classifier: Environment :: Console
Classifier: Intended Audience :: Developers
Classifier: License :: OSI Approved :: MIT License
Classifier: Natural Language :: English
Classifier: Operating System :: OS Independent
Classifier: Programming Language :: Python :: 3
Classifier: Programming Language :: Python :: 3.6
Classifier: Programming Language :: Python :: 3 :: Only
Requires-Python: >=3.6
